bpynodes_lib/__init__.py
bpynodes_lib/base_structs/__init__.py
bpynodes_lib/base_structs/bpy_pynode.py
bpynodes_lib/base_structs/bpy_pynode_socket.py
bpynodes_lib/base_structs/bpy_pynode_tree.py
bpynodes_lib/utils/__init__.py
bpynodes_lib/utils/developer_utils.py
bpynodes_lib/utils/dynamic_props.py
bpynodes_lib/utils/enum_items.py
bpynodes_lib/utils/io.py
bpynodes_lib-1.0.1.dist-info/DESCRIPTION.rst
bpynodes_lib-1.0.1.dist-info/METADATA
bpynodes_lib-1.0.1.dist-info/RECORD
bpynodes_lib-1.0.1.dist-info/WHEEL
bpynodes_lib-1.0.1.dist-info/metadata.json
bpynodes_lib-1.0.1.dist-info/top_level.txt
