Metadata-Version: 2.0
Name: bpynodes-lib
Version: 1.0.1
Summary: Blender Python Nodes extension that provides a python library for creating Python Node systems
Home-page: https://gitlab.com/blenderone/bpynodes_lib1
Author: Jared Webber
Author-email: info@onelvxe.com
License: GNU GPLv3
Keywords: blender bpy nodes custom pynodes
Platform: UNKNOWN
Requires-Python: ~=3.5
